<UnitTest name="PanTilt::PanTiltDegree" status="PASSED"><TestSuite name="OpenCloseSerial" status="PASSED"><TestCase name="DoubleOpen">PASSED</TestCase><TestCase name="closeWithoutOpen">PASSED</TestCase><TestCase name="readingWithoutOpen">PASSED</TestCase><TestCase name="readingWithClosedChannel">PASSED</TestCase><TestCase name="readingWithOpenChannel">PASSED</TestCase></TestSuite><TestSuite name="GetAngle" status="PASSED"><TestCase name="readAndTestRange">PASSED</TestCase><TestCase name="readAndWrite">PASSED</TestCase><TestCase name="keepThe90Range">PASSED</TestCase></TestSuite><TestSuite name="SetAngle" status="PASSED"><TestCase name="readPanOnly">PASSED</TestCase><TestCase name="readTiltOnly">PASSED</TestCase></TestSuite><TestSuite name="ChangeAngle" status="PASSED"><TestCase name="relativeChangesPan">PASSED</TestCase><TestCase name="relativeChangesTilt">PASSED</TestCase></TestSuite></UnitTest>